netbird/__init__.py
netbird/auth.py
netbird/client.py
netbird/exceptions.py
netbird/network_map.py
netbird/models/__init__.py
netbird/models/account.py
netbird/models/common.py
netbird/models/dns.py
netbird/models/event.py
netbird/models/group.py
netbird/models/network.py
netbird/models/peer.py
netbird/models/policy.py
netbird/models/route.py
netbird/models/setup_key.py
netbird/models/token.py
netbird/models/user.py
netbird/resources/__init__.py
netbird/resources/accounts.py
netbird/resources/base.py
netbird/resources/dns.py
netbird/resources/events.py
netbird/resources/groups.py
netbird/resources/networks.py
netbird/resources/peers.py
netbird/resources/policies.py
netbird/resources/routes.py
netbird/resources/setup_keys.py
netbird/resources/tokens.py
netbird/resources/users.py
netbird-1.1.0.dist-info/METADATA
netbird-1.1.0.dist-info/WHEEL
netbird-1.1.0.dist-info/licenses/LICENSE
netbird-1.1.0.dist-info/RECORD
