Metadata-Version: 2.4
Name: netbird
Version: 1.1.0
Summary: Python client for the NetBird API
Project-URL: Homepage, https://github.com/drtinkerer/netbird-python-client
Project-URL: Repository, https://github.com/drtinkerer/netbird-python-client
Project-URL: Documentation, https://github.com/drtinkerer/netbird-python-client
Project-URL: Issues, https://github.com/drtinkerer/netbird-python-client/issues
Project-URL: Changelog, https://github.com/drtinkerer/netbird-python-client/blob/main/CHANGELOG.md
Author-email: Bhushan Rane <eulersidentity2718@gmail.com>
License-Expression: MIT
License-File: LICENSE
Keywords: api,client,mesh,netbird,networking,vpn
Classifier: Development Status :: 5 - Production/Stable
Classifier: Intended Audience :: Developers
Classifier: Intended Audience :: System Administrators
Classifier: License :: OSI Approved :: MIT License
Classifier: Operating System :: OS Independent
Classifier: Programming Language :: Python :: 3
Classifier: Programming Language :: Python :: 3.9
Classifier: Programming Language :: Python :: 3.10
Classifier: Programming Language :: Python :: 3.11
Classifier: Programming Language :: Python :: 3.12
Classifier: Programming Language :: Python :: 3.13
Classifier: Topic :: Internet
Classifier: Topic :: Software Development :: Libraries :: Python Modules
Classifier: Topic :: System :: Networking
Requires-Python: >=3.9
Requires-Dist: httpx>=0.24.0
Requires-Dist: pydantic[email]>=2.0.0
Requires-Dist: typing-extensions>=4.0.0
Provides-Extra: dev
Requires-Dist: black>=23.0.0; extra == 'dev'
Requires-Dist: flake8>=6.0.0; extra == 'dev'
Requires-Dist: isort>=5.12.0; extra == 'dev'
Requires-Dist: mypy>=1.0.0; extra == 'dev'
Requires-Dist: pre-commit>=3.0.0; extra == 'dev'
Requires-Dist: pytest-asyncio>=0.21.0; extra == 'dev'
Requires-Dist: pytest-cov>=4.0.0; extra == 'dev'
Requires-Dist: pytest-httpx>=0.21.0; extra == 'dev'
Requires-Dist: pytest>=7.0.0; extra == 'dev'
Requires-Dist: pyyaml>=6.0.0; extra == 'dev'
Provides-Extra: docs
Requires-Dist: myst-parser>=1.0.0; extra == 'docs'
Requires-Dist: sphinx-autodoc-typehints>=1.23.0; extra == 'docs'
Requires-Dist: sphinx-rtd-theme>=1.2.0; extra == 'docs'
Requires-Dist: sphinx>=6.0.0; extra == 'docs'
